jurispacy_tokenizer/__init__.py
jurispacy_tokenizer/config.py
jurispacy_tokenizer/jurispacy_tokenizer.py
jurispacy_tokenizer-1.2.0.dist-info/WHEEL
jurispacy_tokenizer-1.2.0.dist-info/METADATA
jurispacy_tokenizer-1.2.0.dist-info/RECORD
