Metadata-Version: 2.4
Name: jurispacy-tokenizer
Version: 1.2.0
Summary: Flair tokenizer adapted to French court decisions using spacy tokenization
Keywords: nlp,spacy,flair,tokenizer,legal
Author-email: Cour de cassation <amaury.fouret@justice.fr>
Requires-Python: >=3.10
Classifier: Intended Audience :: Developers
Classifier: License :: OSI Approved :: MIT License
Classifier: Programming Language :: Python :: 3
Classifier: Programming Language :: Python :: 3.10
Classifier: Programming Language :: Python :: 3.11
Classifier: Programming Language :: Python :: 3.12
Requires-Dist: torch==2.7.0
Requires-Dist: scipy<1.13.0
Requires-Dist: spacy==3.6.1
Requires-Dist: flair==0.15.1
Requires-Dist: regex==2024.9.11
Project-URL: Homepage, https://github.com/Cour-de-cassation/jurispacy-tokenizer
Project-URL: Issues, https://github.com/Cour-de-cassation/jurispacy-tokenizer/issues
Project-URL: Repository, https://github.com/Cour-de-cassation/jurispacy-tokenizer
